gbnf/GBNF.py
gbnf/__init__.py
gbnf/grammar_graph/__init__.py
gbnf/grammar_graph/colorize.py
gbnf/grammar_graph/colorize_test.py
gbnf/grammar_graph/get_input_as_code_points.py
gbnf/grammar_graph/get_input_as_code_points_test.py
gbnf/grammar_graph/get_parent_stack_id.py
gbnf/grammar_graph/get_parent_stack_id_test.py
gbnf/grammar_graph/get_serialized_rule_key.py
gbnf/grammar_graph/get_serialized_rule_key_test.py
gbnf/grammar_graph/grammar_graph_types.py
gbnf/grammar_graph/graph.py
gbnf/grammar_graph/graph_node.py
gbnf/grammar_graph/graph_node_test.py
gbnf/grammar_graph/graph_pointer.py
gbnf/grammar_graph/graph_pointer_test.py
gbnf/grammar_graph/graph_test.py
gbnf/grammar_graph/parse_state.py
gbnf/grammar_graph/parse_state_test.py
gbnf/grammar_graph/pointers.py
gbnf/grammar_graph/print.py
gbnf/grammar_graph/print_test.py
gbnf/grammar_graph/rule_ref.py
gbnf/grammar_graph/rule_ref_test.py
gbnf/grammar_graph/type_guards.py
gbnf/grammar_graph/type_guards_test.py
gbnf/grammar_parser/__init__.py
gbnf/grammar_parser/build_rule_stack.py
gbnf/grammar_parser/build_rule_stack_test.py
gbnf/rules_builder/__init__.py
gbnf/rules_builder/is_word_char.py
gbnf/rules_builder/is_word_char_test.py
gbnf/rules_builder/parse_char.py
gbnf/rules_builder/parse_char_test.py
gbnf/rules_builder/parse_name.py
gbnf/rules_builder/parse_name_test.py
gbnf/rules_builder/parse_space.py
gbnf/rules_builder/parse_space_test.py
gbnf/rules_builder/rules_builder.py
gbnf/rules_builder/rules_builder_test.py
gbnf/rules_builder/rules_builder_types.py
gbnf/rules_builder/symbol_ids.py
gbnf/utils/__init__.py
gbnf/utils/is_point_in_range.py
gbnf/utils/is_point_in_range_test.py
gbnf/utils/validate_non_empty.py
gbnf/utils/errors/__init__.py
gbnf/utils/errors/build_error_position.py
gbnf/utils/errors/build_error_position_test.py
gbnf/utils/errors/errors_types.py
gbnf/utils/errors/get_input_as_string.py
gbnf/utils/errors/get_input_as_string_test.py
gbnf/utils/errors/grammar_parse_error.py
gbnf-0.0.30.dist-info/LICENSE
gbnf-0.0.30.dist-info/METADATA
gbnf-0.0.30.dist-info/WHEEL
gbnf-0.0.30.dist-info/top_level.txt
gbnf-0.0.30.dist-info/RECORD
