Metadata-Version: 2.1
Name: gbnf
Version: 0.0.30
Summary: A library for parsing GBNF grammars
Author-email: Ambient Labs <maintainers@gbnf.dev>
Project-URL: Homepage, https://github.com/ambient-labs/GBNF/packages/gbnf
Project-URL: Bug Tracker, https://github.com/ambient-labs/GBNF/packages/gbnf/issues
Classifier: Programming Language :: Python :: 3
Classifier: License :: OSI Approved :: MIT License
Classifier: Operating System :: OS Independent
Requires-Python: >=3.11
License-File: LICENSE
Requires-Dist: pytest-watcher>=0.4.3
